nbsplit/nbsplit.py
notebook_splitter-1.5.dist-info/LICENSE
notebook_splitter-1.5.dist-info/METADATA
notebook_splitter-1.5.dist-info/WHEEL
notebook_splitter-1.5.dist-info/entry_points.txt
notebook_splitter-1.5.dist-info/top_level.txt
notebook_splitter-1.5.dist-info/RECORD
