Metadata-Version: 2.1
Name: notebook-splitter
Version: 1.5
Summary: Jupyter Notebook Splitter
Home-page: https://github.com/AndiH/notebook-splitter
Author: Andreas Herten
Author-email: a.herten@gmail.com
License: MIT
Platform: UNKNOWN
